barista/api/client/__init__.py
barista/api/client/entities.py
barista/api/client/machinery.py
barista_api_client-0.0.2.dist-info/LICENSE
barista_api_client-0.0.2.dist-info/METADATA
barista_api_client-0.0.2.dist-info/WHEEL
barista_api_client-0.0.2.dist-info/top_level.txt
barista_api_client-0.0.2.dist-info/RECORD
