Metadata-Version: 2.1
Name: barista-api-client
Version: 0.0.2
Summary: barista API Client
Home-page: https://github.com/telostat/barista-api-client-python
Author: Vehbi Sinan Tunalioglu
Author-email: vst@vsthost.com
License: Copyright (2017-2019) Vehbi Sinan Tunalioglu.
Requires-Dist: requests (==2.21.0)
Provides-Extra: dev
Requires-Dist: flake8 ; extra == 'dev'
Requires-Dist: ipython ; extra == 'dev'
Requires-Dist: mypy ; extra == 'dev'
Requires-Dist: tox ; extra == 'dev'
Requires-Dist: twine ; extra == 'dev'
Requires-Dist: wheel ; extra == 'dev'
